webvibe/__init__.py
webvibe/webvibe.py
webvibe-2.0.5.dist-info/METADATA
webvibe-2.0.5.dist-info/WHEEL
webvibe-2.0.5.dist-info/entry_points.txt
webvibe-2.0.5.dist-info/top_level.txt
webvibe-2.0.5.dist-info/RECORD
